LICENSE
MANIFEST.in
README.md
setup.py
docs/CONTRIBUTING.md
docs/index.rst
docs/snakescale.rst
snakescale/__init__.py
snakescale/formatters.py
snakescale/resources.py
snakescale/testing.py
snakescale/utils.py
snakescale.egg-info/PKG-INFO
snakescale.egg-info/SOURCES.txt
snakescale.egg-info/dependency_links.txt
snakescale.egg-info/not-zip-safe
snakescale.egg-info/requires.txt
snakescale.egg-info/top_level.txt
snakescale/wrappers/latest/bedtools/subtract/environment.yaml
snakescale/wrappers/latest/bedtools/subtract/meta.yaml
snakescale/wrappers/latest/bedtools/subtract/wrapper.py
snakescale/wrappers/latest/bedtools/subtract/test/Snakefile
snakescale/wrappers/latest/bedtools/subtract/test/data/a.bed
snakescale/wrappers/latest/bedtools/subtract/test/data/b.bed
snakescale/wrappers/latest/bedtools/subtract/test/data/ref.genome
snakescale/wrappers/latest/bedtools/subtract/test/data/result.bed