Metadata-Version: 2.1
Name: snakescale
Version: 0.8.0
Summary: Non-strict wrappers for the data pipelining language Snakemake.
Home-page: https://github.com/clintval/snakescale
Author: clintval
Author-email: valentine.clint@gmail.com
License: MIT
Download-URL: https://github.com/clintval/snakescale/archive/v0.8.0.tar.gz
Project-URL: Documentation, https://snakescale.readthedocs.io
Project-URL: Issue Tracker, https://github.com/clintval/snakescale/issues
Keywords: snakemake pipeline wrapper
Platform: UNKNOWN
Classifier: Development Status :: 2 - Pre-Alpha
Classifier: Intended Audience :: Developers
Classifier: License :: OSI Approved :: MIT License
Classifier: Programming Language :: Python :: 3.6
Classifier: Programming Language :: Python :: 3.7
Provides-Extra: full
